isgri/__init__.py
isgri/__version__.py
isgri/config.py
isgri/catalog/__init__.py
isgri/catalog/builder.py
isgri/catalog/scwquery.py
isgri/catalog/wcs.py
isgri/cli/__init__.py
isgri/cli/main.py
isgri/cli/query.py
isgri/utils/__init__.py
isgri/utils/file_loaders.py
isgri/utils/lightcurve.py
isgri/utils/pif.py
isgri/utils/quality.py
isgri/utils/time_conversion.py
isgri-0.6.1.dist-info/METADATA
isgri-0.6.1.dist-info/WHEEL
isgri-0.6.1.dist-info/entry_points.txt
isgri-0.6.1.dist-info/licenses/LICENSE
isgri-0.6.1.dist-info/RECORD
