Metadata-Version: 2.4
Name: isgri
Version: 0.6.1
Summary: Python package for INTEGRAL IBIS/ISGRI lightcurve analysis
Author: Dominik Patryk Pacholski
License: MIT
License-File: LICENSE
Requires-Python: >=3.9
Requires-Dist: astropy
Requires-Dist: click
Requires-Dist: numpy
Requires-Dist: platformdirs
Requires-Dist: tomli-w
Requires-Dist: tomli>=2.0.0; python_version < '3.11'
